{
  "name": "Javascript 7",
  "game_link": "http://www.google.com",
  "children": [
    {
      "name": "Javascript 7",
      "game_link": "http://www.google.com",
      "children": [
        {
          "name": "Javascript 7",
          "game_link": "http://www.google.com",
          "children": [
            {
              "name": "Javascript 7",
              "game_link": "http://www.google.com"
            },
            {
              "name": "Javascript 8",
              "game_link": "http://www.google.com"
            }
          ]
        },
        {
          "name": "Javascript 5",
          "game_link": "http://www.google.com"
        }
      ]
    },
    {
      "name": "Javascript 6",
      "game_link": "http://www.google.com",
      "children": [
        {
          "name": "Javascript 6",
          "game_link": "http://www.google.com",
          "children": [
            {
              "name": "Javascript 6",
              "game_link": "http://www.google.com"
            },
            {
              "name": "Javascript 3",
              "game_link": "http://www.google.com"
            }
          ]
        },
        {
          "name": "Javascript 1",
          "game_link": "http://www.google.com"
        }
      ]
    }
  ]
}
